odoo10_addon_privacy_partner_report-10.0.1.0.0.99.dev6-py2.7-nspkg.pth
odoo/addons/privacy_partner_report/README.rst
odoo/addons/privacy_partner_report/__init__.py
odoo/addons/privacy_partner_report/__manifest__.py
odoo/addons/privacy_partner_report/controllers/__init__.py
odoo/addons/privacy_partner_report/controllers/main.py
odoo/addons/privacy_partner_report/i18n/de.po
odoo/addons/privacy_partner_report/i18n/fr.po
odoo/addons/privacy_partner_report/i18n/privacy_partner_report.pot
odoo/addons/privacy_partner_report/i18n/pt.po
odoo/addons/privacy_partner_report/report/__init__.py
odoo/addons/privacy_partner_report/report/privacy_partner_xlsx.py
odoo/addons/privacy_partner_report/static/description/icon.png
odoo/addons/privacy_partner_report/views/privacy_menu_view.xml
odoo/addons/privacy_partner_report/views/privacy_report.xml
odoo/addons/privacy_partner_report/wizard/__init__.py
odoo/addons/privacy_partner_report/wizard/privacy_report_partner.py
odoo/addons/privacy_partner_report/wizard/privacy_report_partner_wizard.xml
odoo10_addon_privacy_partner_report-10.0.1.0.0.99.dev6.dist-info/METADATA
odoo10_addon_privacy_partner_report-10.0.1.0.0.99.dev6.dist-info/RECORD
odoo10_addon_privacy_partner_report-10.0.1.0.0.99.dev6.dist-info/WHEEL
odoo10_addon_privacy_partner_report-10.0.1.0.0.99.dev6.dist-info/namespace_packages.txt
odoo10_addon_privacy_partner_report-10.0.1.0.0.99.dev6.dist-info/top_level.txt
